nemdata/__init__.py
nemdata/cli.py
nemdata/config.py
nemdata/constants.py
nemdata/downloader.py
nemdata/loader.py
nemdata/mmsdm.py
nemdata/nemde.py
nemdata/utils.py
nemdata-0.3.7.dist-info/METADATA
nemdata-0.3.7.dist-info/WHEEL
nemdata-0.3.7.dist-info/entry_points.txt
nemdata-0.3.7.dist-info/RECORD
