Metadata-Version: 2.1
Name: nemdata
Version: 0.3.7
Summary: Simple CLI for downloading data for Australia's NEM from AEMO.
License: MIT
Author: Adam Green
Author-email: adam.green@adgefficiency.com
Requires-Python: >=3.10,<3.11
Classifier: License :: OSI Approved :: MIT License
Classifier: Programming Language :: Python :: 3
Classifier: Programming Language :: Python :: 3.10
Requires-Dist: click (>=8.1.3,<9.0.0)
Requires-Dist: lxml (>=4.9.1,<5.0.0)
Requires-Dist: numpy (==1.26.4)
Requires-Dist: pandas (<2.0)
Requires-Dist: pyarrow (>=10.0.1,<11.0.0)
Requires-Dist: pydantic (>=1.10.2,<2.0.0)
Requires-Dist: requests (>=2.28.1,<3.0.0)
Requires-Dist: rich (>=12.6.0,<13.0.0)
